README.txt
setup.py
collective/__init__.py
collective.subtractiveworkflow.egg-info/PKG-INFO
collective.subtractiveworkflow.egg-info/SOURCES.txt
collective.subtractiveworkflow.egg-info/dependency_links.txt
collective.subtractiveworkflow.egg-info/entry_points.txt
collective.subtractiveworkflow.egg-info/namespace_packages.txt
collective.subtractiveworkflow.egg-info/not-zip-safe
collective.subtractiveworkflow.egg-info/requires.txt
collective.subtractiveworkflow.egg-info/top_level.txt
collective/subtractiveworkflow/__init__.py
collective/subtractiveworkflow/browser.py
collective/subtractiveworkflow/configure.zcml
collective/subtractiveworkflow/exportimport.py
collective/subtractiveworkflow/interfaces.py
collective/subtractiveworkflow/react.py
collective/subtractiveworkflow/workflow.py
collective/subtractiveworkflow/tests/__init__.py
collective/subtractiveworkflow/tests/configure.zcml
collective/subtractiveworkflow/tests/test_exportimport.py
collective/subtractiveworkflow/tests/test_permissions.py
docs/HISTORY.txt
docs/INSTALL.txt