Metadata-Version: 1.0
Name: collective.subtractiveworkflow
Version: 2.0b1
Summary: The DCWorkflow giveth and the SubtractiveWorkflow taketh away.
Home-page: http://pypi.python.org/pypi/collective.subtractiveworkflow
Author: Martin Aspeli
Author-email: optilude@gmail.com
License: BSD
Keywords: plone zope cmf workflow permissions
Platform: UNKNOWN
Classifier: Framework :: Plone
Classifier: Programming Language :: Python
Classifier: Topic :: Software Development :: Libraries :: Python Modules
